moran_imaging/__init__.py
moran_imaging/_numba.py
moran_imaging/_version.py
moran_imaging/ari_balance.py
moran_imaging/cae.py
moran_imaging/centralized_conditional_randomization_engine.py
moran_imaging/checks_balance.py
moran_imaging/cnn_clustering.py
moran_imaging/deep_ion_clustering.py
moran_imaging/fast_moran_felzenszwalb_segmentation.py
moran_imaging/local_global_spatial_autocorrelation.py
moran_imaging/moran_hog_clustering.py
moran_imaging/nrdc_clustering.py
moran_imaging/plotting.py
moran_imaging/pseudo_labeling.py
moran_imaging/py.typed
moran_imaging/spatial_kmeans_clustering.py
moran_imaging/spatial_weights_matrix.py
moran_imaging/utils_balance.py
moran_imaging/vmeasure_balance.py
moran_imaging-0.1.1.dist-info/licenses/LICENSE
moran_imaging-0.1.1.dist-info/METADATA
moran_imaging-0.1.1.dist-info/WHEEL
moran_imaging-0.1.1.dist-info/top_level.txt
moran_imaging-0.1.1.dist-info/RECORD
