Metadata-Version: 2.4
Name: Moran_Imaging
Version: 0.1.1
Summary: Spatial analysis of molecular imaging data: spatial dependence and heterogeneity statistics, spatial segmentation, spatial clustering.
Author-email: Leonore Tideman <leonoortideman@gmail.com>
License: BSD 3-Clause License
Project-URL: homepage, https://github.com/vandeplaslab/Moran_Imaging
Project-URL: repository, https://github.com/vandeplaslab/Moran_Imaging
Classifier: Development Status :: 3 - Alpha
Classifier: License :: OSI Approved :: BSD License
Classifier: Natural Language :: English
Classifier: Programming Language :: Python :: 3
Classifier: Programming Language :: Python :: 3.9
Classifier: Programming Language :: Python :: 3.10
Classifier: Programming Language :: Python :: 3.11
Classifier: Programming Language :: Python :: 3.12
Classifier: Programming Language :: Python :: 3.13
Classifier: Typing :: Typed
Requires-Python: >=3.8
License-File: LICENSE
Requires-Dist: joblib>=1.3.0
Requires-Dist: matplotlib>=3.6.0
Requires-Dist: numba>=0.55.0
Requires-Dist: numpy>=1.22.0
Requires-Dist: pandas>=2.0.0
Requires-Dist: tqdm>=4.60.0
Requires-Dist: seaborn
Requires-Dist: h5py
Requires-Dist: scikit-image>=0.20.0
Requires-Dist: scikit-learn>=1.2.0
Requires-Dist: scipy>=1.10.0
Requires-Dist: torch>=2.3.0
Requires-Dist: kornia
Requires-Dist: torchvision
Requires-Dist: byol-pytorch
Requires-Dist: umap-learn>=0.5.0
Provides-Extra: demo
Requires-Dist: jupyterlab; extra == "demo"
Provides-Extra: test
Requires-Dist: pytest>=6.0; extra == "test"
Requires-Dist: pytest-cov; extra == "test"
Provides-Extra: dev
Requires-Dist: ipython; extra == "dev"
Requires-Dist: mypy; extra == "dev"
Requires-Dist: pdbpp; extra == "dev"
Requires-Dist: pre-commit; extra == "dev"
Requires-Dist: rich; extra == "dev"
Requires-Dist: ruff; extra == "dev"
Requires-Dist: Moran_Imaging[demo,test]; extra == "dev"
Dynamic: license-file
